bikeshed
bikeshed-parsy
