Metadata-Version: 2.1
Name: bikeshed
Version: 3.14.2
Summary: A document-authoring tool mainly intended for web specifications.
Home-page: https://github.com/speced/bikeshed/
Author: Tab Atkins-Bittner
Classifier: Development Status :: 5 - Production/Stable
Classifier: License :: Public Domain
Classifier: Operating System :: OS Independent
Classifier: Programming Language :: Python :: 3.7
Classifier: Topic :: Software Development :: Documentation
Requires-Python: >=3.7
License-File: LICENSE
Requires-Dist: aiofiles (==23.1.0)
Requires-Dist: aiohttp (==3.8.4)
Requires-Dist: alive-progress (==3.0.1)
Requires-Dist: attrs (==22.1.0)
Requires-Dist: certifi (==2022.12.7)
Requires-Dist: cssselect (==1.2.0)
Requires-Dist: grapheme (==0.6.0)
Requires-Dist: html5lib (==1.1)
Requires-Dist: isodate (==0.6.1)
Requires-Dist: json-home-client (==1.1.1)
Requires-Dist: lxml (==4.9.2)
Requires-Dist: pillow (==9.5.0)
Requires-Dist: pygments (==2.15.1)
Requires-Dist: requests (==2.29.0)
Requires-Dist: result (==0.8.0)
Requires-Dist: tenacity (==8.2.2)
Requires-Dist: webencodings (==0.5.1)
Requires-Dist: widlparser (==1.1.3)
Requires-Dist: six (==1.16.0) ; python_version >= "2.7" and python_version not in "3.0, 3.1, 3.2, 3.3"
Requires-Dist: urllib3 (==1.26.15) ; python_version >= "2.7" and python_version not in "3.0, 3.1, 3.2, 3.3, 3.4, 3.5"
Requires-Dist: idna (==3.4) ; python_version >= "3.5"
Requires-Dist: async-timeout (==4.0.2) ; python_version >= "3.6"
Requires-Dist: uri-template (==1.2.0) ; python_version >= "3.6"
Requires-Dist: aiosignal (==1.3.1) ; python_version >= "3.7"
Requires-Dist: charset-normalizer (==3.1.0) ; python_version >= "3.7"
Requires-Dist: frozenlist (==1.3.3) ; python_version >= "3.7"
Requires-Dist: multidict (==6.0.4) ; python_version >= "3.7"
Requires-Dist: typing-extensions (==4.5.0) ; python_version >= "3.7"
Requires-Dist: yarl (==1.9.2) ; python_version >= "3.7"
Requires-Dist: about-time (==4.2.1) ; python_version >= "3.7" and python_version < "4.0"
